[{"id":1,"nombre":"ElJAJAS","apellido":"Administrador","identificacion":"196847SS5690","tipoIdentificacion":"CEDULA","rol":"CLIENTE"},{"id":2,"nombre":"Leandro","apellido":"Administrador","identificacion":"196847SS5690","tipoIdentificacion":"CEDULA","rol":"ADMINISTRADOR"},{"id":3,"nombre":"Leandro","apellido":"Administrador","identificacion":"196847SS5690","tipoIdentificacion":"CEDULA","rol":"ADMINISTRADOR"},{"id":4,"nombre":"Leandro","apellido":"Administrador","identificacion":"196847SS5690","tipoIdentificacion":"CEDULA","rol":"ADMINISTRADOR"},{"id":5,"nombre":"Leandro","apellido":"Administrador","identificacion":"196847SS5690","tipoIdentificacion":"CEDULA","rol":"ADMINISTRADOR"}]